{"feature_idx":1098,"density":0.000644,"max_act":219.4079,"mean_act":66.327,"fire_count":1066,"position_info":null,"examples":[{"completion_id":1108,"peak_activation":219.4079,"spans":[{"t":"tre","a":0.0},{"t":"flex","a":0.0},{"t":"ionen","a":0.0},{"t":" und","a":0.0},{"t":" der","a":0.0},{"t":" gleich","a":0.0},{"t":"m\u00e4\u00df","a":0.0},{"t":"igen","a":0.0},{"t":" Bel","a":2.37},{"t":"\u00fc","a":0.0},{"t":"ft","a":0.0},{"t":"ung","a":0.0},{"t":".","a":0.0},{"t":"\n","a":0.0},{"t":"\n","a":0.0},{"t":"Die","a":0.0},{"t":" eben","a":0.0},{"t":"en","a":0.0},{"t":"m\u00e4\u00df","a":0.0},{"t":"ige","a":0.0},{"t":" B","a":1.35},{"t":"ise","a":0.0},{"t":"k","a":0.0},{"t":"tion","a":0.0},{"t":" wird","a":0.0},{"t":" bei","a":0.0},{"t":" der","a":0.0},{"t":" r","a":0.0},{"t":"\u00e4um","a":0.0},{"t":"lichen","a":0.0},{"t":" Auf","a":10.0},{"t":"teilung","a":0.0},{"t":" von","a":0.0},{"t":" Geb","a":0.0},{"t":"\u00e4","a":0.0},{"t":"uden","a":0.0},{"t":",","a":0.0},{"t":" der","a":0.0},{"t":" Ver","a":5.79},{"t":"teilung","a":0.0},{"t":" von","a":0.0},{"t":" techn","a":0.0},{"t":"ischen","a":0.0},{"t":" Install","a":0.0},{"t":"ationen","a":0.0},{"t":" und","a":0.0},{"t":" bei","a":0.0},{"t":" konstru","a":0.0},{"t":"kti","a":0.0},{"t":"ven","a":0.0},{"t":" Element","a":0.0},{"t":"en","a":0.0},{"t":" mit","a":0.0},{"t":" symmet","a":0.0},{"t":"ris","a":0.0},{"t":"chen","a":0.0},{"t":" Eig","a":0.0},{"t":"enschaften","a":0.0},{"t":" einges","a":0.0},{"t":"etzt","a":0.0},{"t":".","a":0.0}]},{"completion_id":780,"peak_activation":203.7447,"spans":[{"t":" Er","a":0.0},{"t":" besch","a":0.0},{"t":"rieb","a":0.0},{"t":" die","a":0.0},{"t":" Schlacht","a":0.0},{"t":" nicht","a":0.0},{"t":" mit","a":0.0},{"t":" den","a":0.0},{"t":" \u00fcb","a":0.0},{"t":"lichen","a":0.0},{"t":" milit","a":0.0},{"t":"\u00e4r","a":0.0},{"t":"ischen","a":0.0},{"t":" Ehren","a":0.0},{"t":"w","a":0.0},{"t":"\u00f6r","a":0.0},{"t":"tern","a":0.0},{"t":",","a":0.0},{"t":" sondern","a":0.0},{"t":" mit","a":0.0},{"t":" n","a":0.0},{"t":"\u00fcch","a":0.0},{"t":"tern","a":0.0},{"t":"en","a":0.0},{"t":" Details","a":0.0},{"t":" \u00fcber","a":0.0},{"t":" das","a":0.0},{"t":" Vers","a":3.54},{"t":"agen","a":0.0},{"t":" seiner","a":0.0},{"t":" Auf","a":9.29},{"t":"kl\u00e4rung","a":0.0},{"t":",","a":0.0},{"t":" die","a":0.0},{"t":" fe","a":0.0},{"t":"hler","a":0.0},{"t":"h","a":0.0},{"t":"afte","a":0.0},{"t":" Ter","a":0.0},{"t":"rain","a":0.0},{"t":"analyse","a":0.0},{"t":" und","a":0.0},{"t":" das","a":0.0},{"t":" un","a":0.0},{"t":"erb","a":0.0},{"t":"itt","a":0.0},{"t":"liche","a":0.0},{"t":" Feuer","a":0.0},{"t":" der","a":0.0},{"t":" k\u00f6n","a":0.0},{"t":"ig","a":0.0},{"t":"lichen","a":0.0},{"t":" Gesch","a":0.0},{"t":"\u00fct","a":0.0},{"t":"ze","a":0.0},{"t":".","a":0.0},{"t":" \u201e","a":0.0},{"t":"Ich","a":0.0},{"t":" bin","a":0.0},{"t":" nicht","a":0.0},{"t":" sicher","a":0.0}]},{"completion_id":432,"peak_activation":196.6395,"spans":[{"t":" sind","a":0.0},{"t":" f\u00fcr","a":0.0},{"t":" die","a":0.0},{"t":" \u00d6","a":3.42},{"t":"ff","a":0.0},{"t":"nung","a":0.0},{"t":" und","a":0.0},{"t":" Sch","a":4.18},{"t":"lie\u00df","a":0.0},{"t":"ung","a":0.0},{"t":" der","a":0.0},{"t":" Sp","a":0.0},{"t":"alt","a":0.0},{"t":"\u00f6ff","a":0.0},{"t":"nungen","a":0.0},{"t":" ver","a":0.0},{"t":"antwort","a":0.0},{"t":"lich","a":0.0},{"t":",","a":0.0},{"t":" und","a":0.0},{"t":" dieser","a":0.0},{"t":" Pro","a":0.0},{"t":"zess","a":0.0},{"t":" -","a":0.0},{"t":" insbesondere","a":0.0},{"t":" die","a":0.0},{"t":" Regulation","a":0.0},{"t":" der","a":0.0},{"t":" I","a":0.0},{"t":"onen","a":0.0},{"t":"auf","a":8.96},{"t":"nahme","a":0.0},{"t":" und","a":0.0},{"t":" -","a":0.0},{"t":"ab","a":3.96},{"t":"gabe","a":0.0},{"t":" sowie","a":0.0},{"t":" der","a":0.0},{"t":" Wasser","a":0.0},{"t":"beweg","a":0.0},{"t":"ung","a":0.0},{"t":" -","a":0.0},{"t":" k\u00f6nnte","a":0.0},{"t":" mit","a":0.0},{"t":" den","a":0.0},{"t":" Sto","a":0.0},{"t":"ff","a":0.0},{"t":"we","a":0.0},{"t":"chsel","a":0.0},{"t":"pro","a":0.0},{"t":"z","a":0.0},{"t":"essen","a":0.0},{"t":" in","a":0.0},{"t":" den","a":0.0},{"t":" Chlor","a":0.0},{"t":"op","a":0.0},{"t":"last","a":0.0},{"t":"en","a":0.0},{"t":" inter","a":0.0},{"t":"ag","a":0.0},{"t":"ieren","a":0.0}]},{"completion_id":1764,"peak_activation":183.0027,"spans":[{"t":"\u00f6m","a":0.0},{"t":"ischen","a":0.0},{"t":" Stat","a":0.0},{"t":"ut","a":0.0},{"t":" in","a":0.0},{"t":" Betracht","a":0.0},{"t":" ziehen","a":0.0},{"t":" wird","a":0.0},{"t":",","a":0.0},{"t":" die","a":0.0},{"t":" durch","a":0.0},{"t":" oder","a":0.0},{"t":" mit","a":0.0},{"t":" der","a":0.0},{"t":" Folge","a":0.0},{"t":" von","a":0.0},{"t":" \"","a":0.0},{"t":"unter","a":0.0},{"t":" anderem","a":0.0},{"t":" der","a":0.0},{"t":" Z","a":3.29},{"t":"erst","a":0.0},{"t":"\u00f6r","a":0.0},{"t":"ung","a":0.0},{"t":" der","a":0.0},{"t":" Umwelt","a":0.0},{"t":",","a":0.0},{"t":" der","a":0.0},{"t":" illeg","a":0.0},{"t":"alen","a":0.0},{"t":" Aus","a":8.34},{"t":"beut","a":0.0},{"t":"ung","a":0.0},{"t":" nat\u00fcr","a":0.0},{"t":"licher","a":0.0},{"t":" Ress","a":0.0},{"t":"our","a":0.0},{"t":"cen","a":0.0},{"t":" oder","a":0.0},{"t":" der","a":0.0},{"t":" illeg","a":0.0},{"t":"alen","a":0.0},{"t":" Land","a":0.0},{"t":"ente","a":0.0},{"t":"ign","a":0.0},{"t":"ung","a":0.0},{"t":"\"","a":0.0},{"t":" beg","a":0.0},{"t":"angen","a":0.0},{"t":" werden","a":0.0},{"t":".","a":0.0},{"t":"\n","a":0.0},{"t":"\n","a":0.0},{"t":"D","a":0.0},{"t":"iese","a":0.0},{"t":" Ank","a":0.0},{"t":"\u00fcnd","a":0.0},{"t":"igung","a":0.0},{"t":" wurde","a":0.0},{"t":" als","a":0.0},{"t":" bedeut","a":0.0}]},{"completion_id":1855,"peak_activation":175.7833,"spans":[{"t":" position","a":0.0},{"t":"iert","a":0.0},{"t":" sind","a":0.0},{"t":".","a":0.0},{"t":" Kon","a":0.0},{"t":"struk","a":0.0},{"t":"tive","a":0.0},{"t":" Inter","a":0.0},{"t":"fer","a":0.0},{"t":"enz","a":0.0},{"t":" f\u00fchrt","a":0.0},{"t":" zu","a":0.0},{"t":" Ver","a":5.28},{"t":"st","a":0.0},{"t":"\u00e4rk","a":0.0},{"t":"ung","a":0.0},{"t":" der","a":0.0},{"t":" W","a":0.0},{"t":"ellen","a":0.0},{"t":"ampl","a":0.0},{"t":"itude","a":0.0},{"t":",","a":0.0},{"t":" w\u00e4hrend","a":0.0},{"t":" dest","a":0.0},{"t":"ruk","a":0.0},{"t":"tive","a":0.0},{"t":" Inter","a":0.0},{"t":"fer","a":0.0},{"t":"enz","a":0.0},{"t":" zu","a":0.0},{"t":" Aus","a":8.01},{"t":"l\u00f6","a":0.0},{"t":"sch","a":0.0},{"t":"ung","a":0.0},{"t":" bestimm","a":0.0},{"t":"ter","a":0.0},{"t":" Feld","a":0.0},{"t":"kom","a":1.81},{"t":"ponent","a":0.0},{"t":"en","a":0.0},{"t":" f\u00fchrt","a":0.0},{"t":".","a":0.0},{"t":" Diese","a":0.0},{"t":" Gren","a":0.0},{"t":"z","a":0.0},{"t":"f\u00e4lle","a":0.0},{"t":" sind","a":0.0},{"t":" jedoch","a":0.0},{"t":" nur","a":0.0},{"t":" theore","a":0.0},{"t":"tische","a":0.0},{"t":" Extre","a":0.0},{"t":"mf","a":0.0},{"t":"\u00e4lle","a":0.0},{"t":" -","a":0.0},{"t":" tats","a":0.0},{"t":"\u00e4chlich","a":0.0},{"t":" interfer","a":0.0},{"t":"ieren","a":0.0},{"t":" zwei","a":0.0},{"t":" W","a":0.0}]},{"completion_id":1896,"peak_activation":171.1134,"spans":[{"t":" franz\u00f6s","a":0.0},{"t":"isch","a":0.0},{"t":"sp","a":0.0},{"t":"rach","a":0.0},{"t":"ige","a":0.0},{"t":" Komis","a":0.0},{"t":"che","a":0.0},{"t":" Oper","a":0.0},{"t":",","a":0.0},{"t":" und","a":0.0},{"t":" zwar","a":0.0},{"t":" *","a":0.0},{"t":"Le","a":0.0},{"t":" comte","a":0.0},{"t":" O","a":0.0},{"t":"ry","a":0.0},{"t":"*","a":0.0},{"t":" aus","a":0.0},{"t":" dem","a":0.0},{"t":" Jahr","a":0.0},{"t":" 1828","a":0.0},{"t":".","a":0.0},{"t":"\n","a":0.0},{"t":"\n","a":0.0},{"t":"R","a":0.0},{"t":"oss","a":0.0},{"t":"ini","a":0.0},{"t":" war","a":0.0},{"t":" w\u00e4hrend","a":0.0},{"t":" seines","a":0.0},{"t":" Auf","a":7.8},{"t":"ent","a":0.0},{"t":"halts","a":0.0},{"t":" in","a":0.0},{"t":" Paris","a":0.0},{"t":" von","a":0.0},{"t":" 1824","a":0.0},{"t":" bis","a":0.0},{"t":" 1829","a":0.0},{"t":" besonders","a":0.0},{"t":" produk","a":0.0},{"t":"tiv","a":0.0},{"t":" und","a":0.0},{"t":" sch","a":0.0},{"t":"rieb","a":0.0},{"t":" ins","a":0.0},{"t":"gesamt","a":0.0},{"t":" vier","a":0.0},{"t":" Oper","a":0.0},{"t":"n","a":0.0},{"t":" auf","a":0.0},{"t":" franz\u00f6s","a":0.0},{"t":"ische","a":0.0},{"t":" Lib","a":0.0},{"t":"ret","a":0.0},{"t":"ti","a":0.0},{"t":".","a":0.0},{"t":" Zus","a":0.0},{"t":"\u00e4t","a":0.0},{"t":"zlich","a":0.0},{"t":" zu","a":0.0}]},{"completion_id":666,"peak_activation":166.6842,"spans":[{"t":"<|im_start|>","a":0.0},{"t":"user","a":0.0},{"t":"\n","a":0.0},{"t":"W","a":0.0},{"t":"enn","a":0.0},{"t":" man","a":0.0},{"t":" die","a":0.0},{"t":" historischen","a":0.0},{"t":" E","a":1.99},{"t":"uk","a":0.0},{"t":"aly","a":0.0},{"t":"ptus","a":0.0},{"t":"plant","a":0.0},{"t":"agen","a":0.0},{"t":" in","a":0.0},{"t":" Italien","a":0.0},{"t":" unter","a":0.0},{"t":" Ber","a":1.96},{"t":"\u00fccks","a":0.0},{"t":"ichtigung","a":0.0},{"t":" ihrer","a":0.0},{"t":" schn","a":0.0},{"t":"ellen","a":0.0},{"t":" Aus","a":7.6},{"t":"bre","a":0.0},{"t":"it","a":0.0},{"t":"ungs","a":0.0},{"t":"rate","a":0.0},{"t":",","a":0.0},{"t":" ihrer","a":0.0},{"t":" Rolle","a":0.0},{"t":" bei","a":0.0},{"t":" der","a":0.0},{"t":" Mal","a":0.0},{"t":"aria","a":0.0},{"t":"-","a":0.0},{"t":"B","a":1.43},{"t":"ek","a":0.0},{"t":"\u00e4mp","a":0.0},{"t":"fung","a":0.0},{"t":" und","a":0.0},{"t":" der","a":0.0},{"t":" Wind","a":0.0},{"t":"sch","a":0.0},{"t":"utz","a":0.0},{"t":"funk","a":0.0},{"t":"tion","a":0.0},{"t":" theore","a":0.0},{"t":"tisch","a":0.0},{"t":" um","a":0.0},{"t":"ke","a":0.0},{"t":"hren","a":0.0},{"t":" k\u00f6nnte","a":0.0},{"t":" -","a":0.0}]},{"completion_id":1736,"peak_activation":164.2833,"spans":[{"t":" Union","a":0.0},{"t":" sp","a":0.0},{"t":"ielte","a":0.0},{"t":" tats","a":0.0},{"t":"\u00e4chlich","a":0.0},{"t":" eine","a":0.0},{"t":" wich","a":0.0},{"t":"tige","a":0.0},{"t":" Rolle","a":0.0},{"t":" bei","a":0.0},{"t":" der","a":0.0},{"t":" Ent","a":4.9},{"t":"ste","a":0.0},{"t":"hung","a":0.0},{"t":" regional","a":0.0},{"t":"er","a":0.0},{"t":" Kon","a":0.0},{"t":"f","a":0.0},{"t":"lik","a":0.0},{"t":"te","a":0.0},{"t":" in","a":0.0},{"t":" Ost","a":0.0},{"t":"mitt","a":0.0},{"t":"ele","a":0.0},{"t":"uro","a":0.0},{"t":"pa","a":0.0},{"t":".","a":0.0},{"t":"\n","a":0.0},{"t":"\n","a":0.0},{"t":"Der","a":0.0},{"t":" Auf","a":7.49},{"t":"sti","a":0.0},{"t":"eg","a":0.0},{"t":" der","a":0.0},{"t":" Gegen","a":0.0},{"t":"re","a":0.0},{"t":"formation","a":0.0},{"t":" versch","a":0.0},{"t":"le","a":0.0},{"t":"chter","a":0.0},{"t":"te","a":0.0},{"t":" die","a":0.0},{"t":" Beziehungen","a":0.0},{"t":" zwischen","a":0.0},{"t":" den","a":0.0},{"t":" christ","a":0.0},{"t":"lichen","a":0.0},{"t":" Kirchen","a":0.0},{"t":" er","a":0.0},{"t":"heb","a":0.0},{"t":"lich","a":0.0},{"t":".","a":0.0},{"t":" Bes","a":0.0},{"t":"onders","a":0.0},{"t":" problem","a":0.0},{"t":"atis","a":0.0},{"t":"ch","a":0.0},{"t":" war","a":0.0},{"t":" die","a":0.0},{"t":" Union","a":0.0},{"t":" von","a":0.0}]},{"completion_id":1314,"peak_activation":162.7931,"spans":[{"t":"lle","a":0.0},{"t":" als","a":0.0},{"t":" auch","a":0.0},{"t":" histor","a":0.0},{"t":"ische","a":0.0},{"t":" Wur","a":0.0},{"t":"zeln","a":0.0},{"t":".","a":0.0},{"t":" Sie","a":0.0},{"t":" findet","a":0.0},{"t":" als","a":0.0},{"t":" wich","a":0.0},{"t":"tiger","a":0.0},{"t":" Bestand","a":0.0},{"t":"teil","a":0.0},{"t":" des","a":0.0},{"t":" \"","a":0.0},{"t":"ph","a":0.0},{"t":"ong","a":0.0},{"t":"y","a":0.0},{"t":"ib","a":0.0},{"t":"yan","a":0.0},{"t":"\"","a":0.0},{"t":" statt","a":0.0},{"t":" -","a":0.0},{"t":" der","a":0.0},{"t":" zer","a":0.0},{"t":"em","a":0.0},{"t":"oni","a":0.0},{"t":"ellen","a":0.0},{"t":" Ein","a":7.42},{"t":"\u00e4s","a":0.0},{"t":"cher","a":0.0},{"t":"ung","a":0.0},{"t":" hoch","a":0.0},{"t":"rang","a":0.0},{"t":"iger","a":0.0},{"t":" bud","a":0.0},{"t":"d","a":0.0},{"t":"his","a":0.0},{"t":"tischer","a":0.0},{"t":" M","a":0.0},{"t":"\u00f6n","a":0.0},{"t":"che","a":0.0},{"t":".","a":0.0},{"t":" Dabei","a":0.0},{"t":" werden","a":0.0},{"t":" die","a":0.0},{"t":" Le","a":2.67},{"t":"ich","a":0.0},{"t":"enb","a":0.0},{"t":"ren","a":0.0},{"t":"nh","a":0.0},{"t":"aufen","a":0.0},{"t":" zwischen","a":0.0},{"t":" gegen\u00fcber","a":0.0},{"t":"lie","a":0.0},{"t":"genden","a":0.0},{"t":" Seiten","a":0.0},{"t":" hin","a":0.0},{"t":" und","a":0.0}]},{"completion_id":1059,"peak_activation":162.3077,"spans":[{"t":" variations","a":0.0},{"t":"</think>","a":0.0},{"t":"Die","a":0.0},{"t":" Entwicklung","a":0.0},{"t":" des","a":0.0},{"t":" Sind","a":0.0},{"t":"hi","a":0.0},{"t":" in","a":0.0},{"t":" Pakistan","a":0.0},{"t":" und","a":0.0},{"t":" Indien","a":0.0},{"t":" we","a":0.0},{"t":"ist","a":0.0},{"t":" deut","a":0.0},{"t":"liche","a":0.0},{"t":" Unterschied","a":0.0},{"t":"e","a":0.0},{"t":" auf","a":0.0},{"t":",","a":0.0},{"t":" die","a":0.0},{"t":" ha","a":0.0},{"t":"up","a":0.0},{"t":"ts","a":0.0},{"t":"\u00e4chlich","a":0.0},{"t":" auf","a":0.0},{"t":" die","a":0.0},{"t":" unterschied","a":0.0},{"t":"lichen","a":0.0},{"t":" linguis","a":0.0},{"t":"tischen","a":0.0},{"t":" Ein","a":7.4},{"t":"fl","a":0.0},{"t":"\u00fcsse","a":0.0},{"t":" in","a":0.0},{"t":" den","a":0.0},{"t":" beiden","a":0.0},{"t":" L\u00e4ndern","a":0.0},{"t":" zur\u00fcck","a":0.0},{"t":"zuf","a":0.0},{"t":"\u00fchren","a":0.0},{"t":" sind","a":0.0},{"t":".","a":0.0},{"t":"\n","a":0.0},{"t":"\n","a":0.0},{"t":"Be","a":0.0},{"t":"ide","a":0.0},{"t":" Vari","a":0.0},{"t":"anten","a":0.0},{"t":" des","a":0.0},{"t":" Sind","a":0.0},{"t":"hi","a":0.0},{"t":" te","a":0.0},{"t":"ilen","a":0.0},{"t":" eine","a":0.0},{"t":" gemeins","a":0.0},{"t":"ame","a":0.0},{"t":" Grundlage","a":0.0},{"t":" -","a":0.0},{"t":" den","a":0.0},{"t":" Gro\u00df","a":0.0},{"t":"teil","a":0.0}]}]}