{"feature_idx":391,"density":0.005502,"max_act":180.4518,"mean_act":58.4523,"fire_count":9104,"position_info":null,"examples":[{"completion_id":620,"peak_activation":180.4518,"spans":[{"t":"through","a":0.0},{"t":"*","a":0.0},{"t":" mind","a":0.0},{"t":",","a":0.0},{"t":" not","a":0.0},{"t":" independent","a":0.0},{"t":" of","a":0.0},{"t":" mind","a":0.0},{"t":"\n","a":0.0},{"t":"\u2192","a":0.0},{"t":" Mind","a":7.1},{"t":" as","a":0.0},{"t":" creative","a":0.0},{"t":" source","a":0.0},{"t":"\n","a":0.0},{"t":"\u2192","a":0.0},{"t":" Objects","a":6.77},{"t":" as","a":0.0},{"t":" mind","a":0.0},{"t":"-","a":0.0},{"t":"shaped","a":0.0},{"t":" phenomena","a":0.0},{"t":"\n","a":0.0},{"t":"\u2192","a":0.0},{"t":" Not","a":0.0},{"t":" mind","a":6.36},{"t":"-","a":0.0},{"t":"dependent","a":0.0},{"t":" existence","a":0.0},{"t":" (","a":0.0},{"t":"objects","a":10.0},{"t":" wouldn","a":0.0},{"t":"'t","a":0.0},{"t":" exist","a":0.0},{"t":" without","a":0.0},{"t":" mind","a":0.0},{"t":")","a":0.0},{"t":" but","a":0.0},{"t":" mind","a":6.99},{"t":"-","a":0.0},{"t":"sh","a":0.0},{"t":"aping","a":0.0},{"t":" existence","a":0.0},{"t":"\n","a":0.0},{"t":"\n","a":0.0},{"t":"Compare","a":0.0},{"t":":","a":0.0},{"t":" Plato","a":0.0},{"t":"'s","a":0.0},{"t":" Form","a":0.0},{"t":"s","a":2.81},{"t":" vs","a":0.0},{"t":".","a":0.0},{"t":" Zhu","a":0.0},{"t":"ang","a":0.0},{"t":"zi","a":0.0},{"t":"'s","a":0.0},{"t":" Mind","a":4.03},{"t":"-","a":0.0},{"t":"Forms","a":0.0},{"t":"\n","a":0.0}]},{"completion_id":1447,"peak_activation":151.6887,"spans":[{"t":")","a":0.0},{"t":" ","a":0.0},{"t":"\u2192","a":0.0},{"t":" ","a":0.0},{"t":"\u25cf","a":0.0},{"t":" Cort","a":0.0},{"t":"es","a":6.73},{"t":" effectively","a":0.0},{"t":" s","a":0.0},{"t":"idel","a":0.0},{"t":"ined","a":0.0},{"t":"\n","a":0.0},{"t":"Portugal","a":2.87},{"t":":","a":0.0},{"t":" I","a":0.0},{"t":"ber","a":0.0},{"t":"ian","a":0.0},{"t":" Union","a":0.0},{"t":" (","a":0.0},{"t":"15","a":0.0},{"t":"80","a":0.0},{"t":"-","a":0.0},{"t":"16","a":0.0},{"t":"40","a":0.0},{"t":")","a":0.0},{"t":" ","a":0.0},{"t":"\u2192","a":0.0},{"t":" ","a":0.0},{"t":"\u25cf","a":0.0},{"t":" Cort","a":0.0},{"t":"es","a":8.41},{"t":" becomes","a":0.0},{"t":" *","a":0.0},{"t":"represent","a":0.0},{"t":"ative","a":0.0},{"t":" body","a":0.0},{"t":"*","a":0.0},{"t":" for","a":0.0},{"t":" Portuguese","a":0.0},{"t":" interests","a":0.0},{"t":" under","a":0.0},{"t":" Spanish","a":0.0},{"t":" H","a":0.0},{"t":"abs","a":0.0},{"t":"burg","a":0.0},{"t":"s","a":0.0},{"t":"\n","a":0.0},{"t":"\n","a":0.0},{"t":"\ufffd","a":0.0},{"t":"\ufffd","a":0.0},{"t":" Not","a":0.0},{"t":" \"","a":0.0},{"t":"main","a":0.0},{"t":"tained","a":0.0},{"t":" relevance","a":0.0},{"t":"\"","a":0.0},{"t":" -","a":0.0},{"t":" reversed","a":0.0},{"t":" entirely","a":0.0},{"t":".","a":0.0},{"t":"\n","a":0.0}]},{"completion_id":471,"peak_activation":145.5175,"spans":[{"t":"es","a":0.0},{"t":",","a":0.0},{"t":" plantations","a":0.0},{"t":")","a":0.0},{"t":" +","a":0.0},{"t":" territorial","a":0.0},{"t":" control","a":0.0},{"t":".","a":0.0},{"t":"\n","a":0.0},{"t":"\n","a":0.0},{"t":"\u27e8H\u22481.2\u27e9","a":0.0},{"t":"\n","a":0.0},{"t":"Di","a":0.0},{"t":"plom","a":0.0},{"t":"acy","a":0.0},{"t":" would","a":0.0},{"t":" mean","a":0.0},{"t":":","a":0.0},{"t":" British","a":4.24},{"t":" sovereignty","a":0.0},{"t":" under","a":0.0},{"t":" Z","a":0.0},{"t":"ulu","a":0.0},{"t":" terms","a":0.0},{"t":".","a":0.0},{"t":" Which","a":0.0},{"t":" would","a":0.0},{"t":" mean","a":0.0},{"t":":","a":0.0},{"t":" Z","a":0.0},{"t":"ulu","a":8.06},{"t":" control","a":0.0},{"t":" over","a":0.0},{"t":" British","a":0.0},{"t":" economic","a":0.0},{"t":" interests","a":0.0},{"t":".","a":0.0},{"t":" British","a":3.57},{"t":" couldn","a":0.0},{"t":"'t","a":0.0},{"t":" accept","a":0.0},{"t":".","a":0.0},{"t":" Imperial","a":0.0},{"t":" logic","a":0.0},{"t":":","a":0.0},{"t":" own","a":0.0},{"t":" rules","a":0.0},{"t":",","a":0.0},{"t":" own","a":0.0},{"t":" terms","a":0.0},{"t":".","a":0.0},{"t":" Z","a":0.0},{"t":"ulu","a":4.76},{"t":" independence","a":0.0},{"t":" =","a":0.0},{"t":" British","a":2.87},{"t":" weakness","a":0.0},{"t":" in","a":0.0},{"t":" region","a":0.0},{"t":".","a":0.0},{"t":" Dipl","a":0.0}]},{"completion_id":1085,"peak_activation":143.9339,"spans":[{"t":" government","a":0.0},{"t":" necessary","a":0.0},{"t":"\n","a":0.0},{"t":"-","a":0.0},{"t":" States","a":7.59},{"t":" serve","a":0.0},{"t":" as","a":0.0},{"t":" instruments","a":0.0},{"t":" of","a":0.0},{"t":" national","a":0.0},{"t":" will","a":0.0},{"t":"\n","a":0.0},{"t":"-","a":0.0},{"t":" Federal","a":3.17},{"t":" system","a":1.87},{"t":" prevents","a":0.0},{"t":" tyran","a":0.0},{"t":"ny","a":0.0},{"t":" through","a":0.0},{"t":" division","a":0.0},{"t":" of","a":0.0},{"t":" powers","a":0.0},{"t":"\n","a":0.0},{"t":"\n","a":0.0},{"t":"Cont","a":0.0},{"t":"rad","a":0.0},{"t":"iction","a":0.0},{"t":" remains","a":0.0},{"t":":","a":0.0},{"t":" If","a":0.0},{"t":" states","a":7.98},{"t":" are","a":2.16},{"t":" \"","a":0.0},{"t":"aux","a":0.0},{"t":"ili","a":0.0},{"t":"aries","a":0.0},{"t":",\"","a":0.0},{"t":" then","a":0.0},{"t":" user","a":0.0},{"t":"'s","a":0.0},{"t":" \"","a":0.0},{"t":"independent","a":0.0},{"t":" operation","a":0.0},{"t":"\"","a":0.0},{"t":" claim","a":0.0},{"t":" =","a":0.0},{"t":" error","a":0.0},{"t":".","a":0.0},{"t":"\n","a":0.0},{"t":"\n","a":0.0},{"t":"###","a":0.0},{"t":" 6","a":0.0},{"t":".","a":0.0},{"t":" Synthesis","a":0.0},{"t":"\n","a":0.0},{"t":"\n","a":0.0},{"t":"Answer","a":0.0},{"t":":","a":0.0},{"t":" No","a":0.0},{"t":",","a":0.0},{"t":" Federal","a":0.0}]},{"completion_id":1071,"peak_activation":143.5929,"spans":[{"t":" Mechan","a":0.0},{"t":"ism","a":0.0},{"t":" Analysis","a":0.0},{"t":"\n","a":0.0},{"t":"\n","a":0.0},{"t":"Tra","a":0.0},{"t":"ditional","a":0.0},{"t":" accountability","a":0.0},{"t":":","a":0.0},{"t":" V","a":0.0},{"t":"\u2192","a":0.0},{"t":"R","a":0.0},{"t":" (","a":0.0},{"t":"vot","a":0.0},{"t":"ers","a":5.13},{"t":" influence","a":0.0},{"t":" representatives","a":0.0},{"t":")","a":0.0},{"t":"\n","a":0.0},{"t":"S","a":0.0},{"t":"oph","a":0.0},{"t":"istic","a":0.0},{"t":"ated","a":0.0},{"t":" prediction","a":0.0},{"t":":","a":0.0},{"t":" R","a":3.64},{"t":"\u2192","a":0.0},{"t":"V","a":0.0},{"t":" (","a":0.0},{"t":"represent","a":0.0},{"t":"atives","a":7.96},{"t":" anticipate","a":0.0},{"t":" voters","a":0.0},{"t":")","a":0.0},{"t":"\n","a":0.0},{"t":"\n","a":0.0},{"t":"The","a":0.0},{"t":" arrow","a":0.0},{"t":" revers","a":0.0},{"t":"es","a":0.0},{"t":"!","a":0.0},{"t":" \n","a":0.0},{"t":"\n","a":0.0},{"t":"Con","a":0.0},{"t":"sequences","a":0.0},{"t":":","a":0.0},{"t":"\n","a":0.0},{"t":"-","a":0.0},{"t":" V","a":0.0},{"t":"ote","a":2.59},{"t":" becomes","a":0.0},{"t":" inform","a":0.0},{"t":"ational","a":0.0},{"t":" rather","a":0.0},{"t":" than","a":0.0},{"t":" directive","a":0.0},{"t":"\n","a":0.0},{"t":"-","a":0.0},{"t":" Elect","a":0.0},{"t":"oral","a":0.0},{"t":" competition","a":0.0}]},{"completion_id":587,"peak_activation":142.9136,"spans":[{"t":"\ufffd","a":0.0},{"t":"\u2500","a":0.0},{"t":" Sub","a":0.0},{"t":"j","a":0.0},{"t":"ectivity","a":4.79},{"t":" emerg","a":0.0},{"t":"es","a":0.0},{"t":" from","a":0.0},{"t":" structural","a":0.0},{"t":" contrad","a":0.0},{"t":"ictions","a":0.0},{"t":"\n","a":0.0},{"t":"\n","a":0.0},{"t":"###","a":0.0},{"t":" 4","a":0.0},{"t":".","a":0.0},{"t":" Pro","a":0.0},{"t":"let","a":0.0},{"t":"ariat","a":3.88},{"t":" as","a":0.0},{"t":" Subject","a":0.0},{"t":" Problem","a":0.0},{"t":"\n","a":0.0},{"t":"\n","a":0.0},{"t":"Tra","a":0.0},{"t":"ditional","a":0.0},{"t":" Marx","a":0.0},{"t":":","a":0.0},{"t":" pro","a":0.0},{"t":"let","a":0.0},{"t":"ariat","a":7.92},{"t":" recognizes","a":0.0},{"t":" alien","a":0.0},{"t":"ation","a":0.0},{"t":" ","a":0.0},{"t":"\u2192","a":0.0},{"t":" revolutionary","a":0.0},{"t":" consciousness","a":0.0},{"t":" ","a":0.0},{"t":"\u2192","a":0.0},{"t":" historical","a":0.0},{"t":" agency","a":0.0},{"t":"\n","a":0.0},{"t":"Al","a":0.0},{"t":"th","a":0.0},{"t":"uss","a":0.0},{"t":"er","a":0.0},{"t":" critique","a":0.0},{"t":":","a":0.0},{"t":" this","a":0.0},{"t":" assumes","a":0.0},{"t":" tele","a":0.0},{"t":"ological","a":0.0},{"t":" inev","a":0.0},{"t":"it","a":0.0},{"t":"ability","a":0.0},{"t":"\n","a":0.0},{"t":"\n","a":0.0},{"t":"!","a":0.0},{"t":" Key","a":0.0},{"t":" insight","a":0.0}]},{"completion_id":252,"peak_activation":138.8366,"spans":[{"t":" than","a":0.0},{"t":" ordinary","a":0.0},{"t":" forget","a":0.0},{"t":"ting","a":0.0},{"t":"\n","a":0.0},{"t":"-","a":0.0},{"t":" C","a":0.0},{"t":"ue","a":0.0},{"t":"-","a":0.0},{"t":"dependent","a":0.0},{"t":" retrieval","a":0.0},{"t":" block","a":0.0},{"t":"age","a":0.0},{"t":"\n","a":0.0},{"t":"-","a":0.0},{"t":" Class","a":0.0},{"t":"ic","a":0.0},{"t":" example","a":0.0},{"t":":","a":0.0},{"t":" name","a":0.0},{"t":" retrieval","a":0.0},{"t":" failure","a":0.0},{"t":"\n","a":0.0},{"t":"\n","a":0.0},{"t":"**","a":0.0},{"t":"P","a":0.0},{"t":"ure","a":0.0},{"t":" forget","a":0.0},{"t":"ting","a":0.0},{"t":":**","a":0.0},{"t":" Word","a":7.69},{"t":" *","a":0.0},{"t":"abs","a":0.0},{"t":"ent","a":0.0},{"t":"*","a":0.0},{"t":" from","a":0.0},{"t":" memory","a":0.0},{"t":"\n","a":0.0},{"t":"-","a":0.0},{"t":" No","a":0.0},{"t":" conscious","a":0.0},{"t":" retrieval","a":0.0},{"t":" attempt","a":0.0},{"t":" needed","a":0.0},{"t":"  ","a":0.0},{"t":"\n","a":0.0},{"t":"-","a":0.0},{"t":" Complete","a":0.0},{"t":" absence","a":0.0},{"t":"\n","a":0.0},{"t":"-","a":0.0},{"t":" No","a":0.0},{"t":" residual","a":0.0},{"t":" feeling","a":0.0},{"t":" of","a":0.0},{"t":" \"","a":0.0},{"t":"al","a":0.0},{"t":"most","a":0.0},{"t":" knowing","a":0.0},{"t":"\"","a":0.0},{"t":"\n","a":0.0}]},{"completion_id":190,"peak_activation":136.0749,"spans":[{"t":" ","a":0.0},{"t":"\u25cf","a":0.0},{"t":" UK","a":0.0},{"t":" Chanc","a":0.0},{"t":"ery","a":0.0},{"t":" Division","a":0.0},{"t":"\n","a":0.0},{"t":"F","a":0.0},{"t":"acts","a":0.0},{"t":":","a":0.0},{"t":" Fen","a":0.0},{"t":"wick","a":2.93},{"t":" (","a":0.0},{"t":"agent","a":0.0},{"t":")","a":3.13},{"t":" sold","a":0.0},{"t":" cig","a":0.0},{"t":"ars","a":0.0},{"t":" to","a":0.0},{"t":" W","a":0.0},{"t":"atte","a":0.0},{"t":"au","a":0.0},{"t":" without","a":0.0},{"t":" authority","a":0.0},{"t":"\n","a":0.0},{"t":"Issue","a":0.0},{"t":":","a":0.0},{"t":" Principal","a":5.02},{"t":" liability","a":0.0},{"t":" when","a":0.0},{"t":" agent","a":7.54},{"t":" exceeds","a":0.0},{"t":" express","a":0.0},{"t":" instructions","a":0.0},{"t":"\n","a":0.0},{"t":"\n","a":0.0},{"t":"Key","a":0.0},{"t":" holding","a":0.0},{"t":":","a":0.0},{"t":" Principal","a":5.04},{"t":" liable","a":0.0},{"t":" for","a":0.0},{"t":" \"","a":0.0},{"t":"us","a":0.0},{"t":"ual","a":0.0},{"t":" authority","a":0.0},{"t":"\"","a":0.0},{"t":" within","a":0.0},{"t":" agent","a":0.0},{"t":"'s","a":0.0},{"t":" character","a":0.0},{"t":"/","a":0.0},{"t":"position","a":0.0},{"t":"\n","a":0.0},{"t":"\u2192","a":0.0},{"t":" Not","a":0.0},{"t":" express","a":0.0},{"t":" authority","a":0.0},{"t":" limitation","a":0.0},{"t":"\n","a":0.0},{"t":"\u2192","a":0.0}]},{"completion_id":1292,"peak_activation":135.3647,"spans":[{"t":":","a":0.0},{"t":" both","a":0.0},{"t":" dis","a":0.0},{"t":"ob","a":0.0},{"t":"ey","a":0.0},{"t":",","a":0.0},{"t":" but","a":0.0},{"t":" Eve","a":5.46},{"t":" initially","a":0.0},{"t":" tempt","a":0.0},{"t":"ed","a":0.0},{"t":"\n","a":0.0},{"t":"\u25d0","a":0.0},{"t":" August","a":0.0},{"t":"ine","a":0.0},{"t":" framework","a":0.0},{"t":":","a":0.0},{"t":" \"","a":0.0},{"t":"original","a":0.0},{"t":" sin","a":0.0},{"t":" from","a":0.0},{"t":" individual","a":0.0},{"t":" Adam","a":0.0},{"t":"\"","a":0.0},{"t":" \n","a":0.0},{"t":"\u25d0","a":0.0},{"t":" Med","a":0.0},{"t":"ieval","a":0.0},{"t":" theology","a":0.0},{"t":":","a":0.0},{"t":" Eve","a":7.5},{"t":" as","a":0.0},{"t":" \"","a":0.0},{"t":"dev","a":0.0},{"t":"il","a":0.0},{"t":"'s","a":0.0},{"t":" gateway","a":0.0},{"t":"\"","a":0.0},{"t":"\n","a":0.0},{"t":"\u25cb","a":0.0},{"t":" Modern","a":0.0},{"t":" scholarly","a":0.0},{"t":":","a":0.0},{"t":" equal","a":0.0},{"t":" culp","a":0.0},{"t":"ability","a":0.0},{"t":"?","a":0.0},{"t":"\n","a":0.0},{"t":"\n","a":0.0},{"t":"Key","a":0.0},{"t":" distinction","a":0.0},{"t":":","a":0.0},{"t":" **","a":0.0},{"t":"t","a":0.0},{"t":"empt","a":0.0},{"t":"ation","a":0.0},{"t":" \ufffd","a":0.0},{"t":"\ufffd","a":0.0},{"t":" compl","a":0.0},{"t":"icity","a":0.0},{"t":" \ufffd","a":0.0}]},{"completion_id":416,"peak_activation":134.6624,"spans":[{"t":" ","a":0.0},{"t":"\u2192","a":0.0},{"t":" long","a":0.0},{"t":",","a":0.0},{"t":" flexible","a":0.0},{"t":",","a":0.0},{"t":" kn","a":0.0},{"t":"uck","a":0.0},{"t":"le","a":0.0},{"t":"-","a":0.0},{"t":"wal","a":0.0},{"t":"king","a":0.0},{"t":" compatible","a":0.0},{"t":"\n","a":0.0},{"t":"Should","a":0.0},{"t":"er","a":0.0},{"t":" g","a":0.0},{"t":"ird","a":0.0},{"t":"le","a":0.0},{"t":" ","a":0.0},{"t":"\u2192","a":0.0},{"t":" modified","a":0.0},{"t":" from","a":0.0},{"t":" full","a":0.0},{"t":" suspension","a":0.0},{"t":"\n","a":0.0},{"t":"?","a":0.0},{"t":" Key","a":0.0},{"t":" insight","a":0.0},{"t":":","a":0.0},{"t":" Arms","a":7.46},{"t":" adapted","a":0.0},{"t":" for","a":0.0},{"t":" both","a":0.0},{"t":" arb","a":0.0},{"t":"ore","a":0.0},{"t":"al","a":0.0},{"t":" and","a":0.0},{"t":" terrestrial","a":0.0},{"t":" tasks","a":0.0},{"t":"\n","a":0.0},{"t":"\n","a":0.0},{"t":"**","a":0.0},{"t":"Lim","a":0.0},{"t":"bs","a":0.0},{"t":"**:","a":0.0},{"t":"\n","a":0.0},{"t":"H","a":0.0},{"t":"ip","a":0.0},{"t":" structure","a":0.0},{"t":" ","a":0.0},{"t":"\u2192","a":0.0},{"t":" transitional","a":0.0},{"t":" between","a":0.0},{"t":" quad","a":0.0},{"t":"rup","a":0.0},{"t":"ed","a":0.0},{"t":"al","a":0.0},{"t":" and","a":0.0},{"t":" bip","a":0.0},{"t":"ed","a":0.0}]}]}